MANIFEST.in
README.txt
setup.cfg
setup.py
csci/__init__.py
csci.images.egg-info/PKG-INFO
csci.images.egg-info/SOURCES.txt
csci.images.egg-info/dependency_links.txt
csci.images.egg-info/entry_points.txt
csci.images.egg-info/namespace_packages.txt
csci.images.egg-info/not-zip-safe
csci.images.egg-info/paster_plugins.txt
csci.images.egg-info/requires.txt
csci.images.egg-info/top_level.txt
csci/images/README.txt
csci/images/__init__.py
csci/images/config.py
csci/images/configure.zcml
csci/images/browser/__init__.py
csci/images/browser/configure.zcml
csci/images/content/__init__.py
csci/images/content/configure.zcml
csci/images/interfaces/__init__.py
csci/images/portlets/__init__.py
csci/images/portlets/configure.zcml
csci/images/portlets/csciimages.pt
csci/images/portlets/csciimages.py
csci/images/profiles/default/factorytool.xml
csci/images/profiles/default/metadata.xml
csci/images/profiles/default/portlets.xml
csci/images/profiles/default/types.xml
csci/images/tests/__init__.py
csci/images/tests/base.py
csci/images/tests/base_csciimages.py
csci/images/tests/test_csciimages.py
csci/images/tests/test_doctest.py