Metadata-Version: 1.0
Name: csci.images
Version: 1.0dev
Summary: Display images for news and events
Home-page: www.cannonscientific.com
Author: Peter Dyson
Author-email: pdyson@cannonscientific.com
License: GPL
Keywords: plone images events news
Platform: UNKNOWN
Classifier: Framework :: Plone
Classifier: Intended Audience :: Developers
Classifier: Topic :: Software Development :: Libraries :: Python Modules
Classifier: License :: OSI Approved :: GNU General Public License (GPL)
